{"url": "https://fs.fang.anjuke.com/loupan/canshu-243928.html", "projname": "博澳城", "xzarea": "佛山区域", "price": "14000", "area": "顺德", "position": "大良", "developer": "佛山市顺德区兆辉投资置业有限公司,佛山市顺德区兆锐房地产有限公司"}
{"url": "https://zh.fang.anjuke.com/loupan/canshu-409165.html", "projname": "保利时代", "xzarea": "珠海区域", "price": "21000", "area": "金湾", "position": "金湾", "developer": "珠海祥越投资有限公司"}
{"url": "https://fs.fang.anjuke.com/loupan/canshu-416916.html", "projname": "绿地丽雅香榭花城", "xzarea": "佛山区域", "price": "13500", "area": "南海", "position": "狮山", "developer": "佛山市丽雅翠湖尚筑房地产开发有限公司"}
{"url": "https://zh.fang.anjuke.com/loupan/canshu-256081.html", "projname": "中邦·浪琴湾", "xzarea": "珠海区域", "price": "32000", "area": "横琴", "position": "横琴", "developer": "珠海中邦房地产开发有限公司"}
{"url": "https://zs.fang.anjuke.com/loupan/canshu-429234.html", "projname": "保利香槟国际", "xzarea": "中山区域", "price": "10000", "area": "[查看地图]", "position": "", "developer": "黄圃镇 黄圃镇"}
{"url": "https://fs.fang.anjuke.com/loupan/canshu-419256.html", "projname": "瑞日天下花园", "xzarea": "佛山区域", "price": 0, "area": "高明", "position": "荷城", "developer": "佛山市雅域房地产有限公司"}
{"url": "https://zh.fang.anjuke.com/loupan/canshu-430034.html", "projname": "湾区星座", "xzarea": "珠海区域", "price": "22000", "area": "横琴", "position": "横琴", "developer": "珠海市奇泰置业有限公司"}
{"url": "https://fs.fang.anjuke.com/loupan/canshu-423111.html", "projname": "碧桂园奥斯汀", "xzarea": "佛山区域", "price": 0, "area": "三水", "position": "西南", "developer": "佛山市三水西南碧桂园房地产开发有限公司"}
{"url": "https://zh.fang.anjuke.com/loupan/canshu-414966.html", "projname": "中安广场", "xzarea": "珠海区域", "price": "33000", "area": "香洲", "position": "香洲", "developer": "珠海市钧策商贸发展有限公司"}
{"url": "https://fs.fang.anjuke.com/loupan/canshu-430769.html", "projname": "时代家", "xzarea": "佛山区域", "price": 0, "area": "南海", "position": "里水", "developer": "佛山市时代天宇房地产开发有限公司"}
{"url": "https://zh.fang.anjuke.com/loupan/canshu-401016.html", "projname": "横琴梧桐树大厦", "xzarea": "珠海区域", "price": 0, "area": "横琴", "position": "横琴", "developer": "珠海横琴国开投资有限公司"}
{"url": "https://fs.fang.anjuke.com/loupan/canshu-243910.html", "projname": "上林苑", "xzarea": "佛山区域", "price": "14000", "area": "南海", "position": "狮山", "developer": "佛山市南海恒胜置业有限公司"}
{"url": "https://zh.fang.anjuke.com/loupan/canshu-412477.html", "projname": "九洲保利天和", "xzarea": "珠海区域", "price": "22000", "area": "金湾", "position": "金湾", "developer": "珠海天志发展置业有限公司"}
{"url": "https://zh.fang.anjuke.com/loupan/canshu-410990.html", "projname": "华发又一城", "xzarea": "珠海区域", "price": "16000", "area": "斗门", "position": "斗门", "developer": "珠海华郡房产开发有限公司"}
{"url": "https://fs.fang.anjuke.com/loupan/canshu-411756.html", "projname": "勤天汇", "xzarea": "佛山区域", "price": "9000", "area": "高明", "position": "荷城", "developer": "佛山勤天汇房地产开发有限公司"}
{"url": "https://fs.fang.anjuke.com/loupan/canshu-411218.html", "projname": "保利珑门", "xzarea": "佛山区域", "price": "20000", "area": "南海", "position": "大沥", "developer": "百隆房地产有限公司"}
{"url": "https://zh.fang.anjuke.com/loupan/canshu-414101.html", "projname": "华策帝景湾", "xzarea": "珠海区域", "price": "32000", "area": "香洲", "position": "香洲", "developer": "珠海香洋实业有限公司"}
{"url": "https://fs.fang.anjuke.com/loupan/canshu-243855.html", "projname": "碧桂园翡翠湾", "xzarea": "佛山区域", "price": "9000", "area": "南海", "position": "西樵", "developer": ""}
{"url": "https://zh.fang.anjuke.com/loupan/canshu-256061.html", "projname": "佳兆业水岸华都", "xzarea": "珠海区域", "price": "35000", "area": "香洲", "position": "香洲", "developer": "珠海市展大房地产开发有限公司"}
{"url": "https://zh.fang.anjuke.com/loupan/canshu-400607.html", "projname": "优越香格里", "xzarea": "珠海区域", "price": "17500", "area": "中山市", "position": "中山市", "developer": "中山市兴源房地产发展有限公司"}
{"url": "https://fs.fang.anjuke.com/loupan/canshu-415049.html", "projname": "金茂绿岛湖", "xzarea": "佛山区域", "price": "18000", "area": "禅城", "position": "南庄", "developer": ""}
{"url": "https://zh.fang.anjuke.com/loupan/canshu-256049.html", "projname": "K2·荔枝湾", "xzarea": "珠海区域", "price": "53000", "area": "横琴", "position": "横琴", "developer": "珠海荔枝湾投资发展有限公司"}
{"url": "https://zh.fang.anjuke.com/loupan/canshu-256093.html", "projname": "中铁·诺德国际", "xzarea": "珠海区域", "price": "41700", "area": "香洲", "position": "香洲", "developer": "珠海中铁诺德投资有限公司"}
{"url": "https://zh.fang.anjuke.com/loupan/canshu-418692.html", "projname": "奥园·观山海", "xzarea": "珠海区域", "price": "22000", "area": "横琴", "position": "横琴", "developer": "中国奥园地产集团股份有限公司"}
{"url": "https://zh.fang.anjuke.com/loupan/canshu-404102.html", "projname": "惠景慧园", "xzarea": "珠海区域", "price": "14000", "area": "香洲", "position": "香洲", "developer": "珠海市高新建设投资有限公司"}
{"url": "https://zh.fang.anjuke.com/loupan/canshu-432094.html", "projname": "远洋繁花里", "xzarea": "珠海区域", "price": "8500", "area": "中山市", "position": "中山市", "developer": "中山市哈特贸易有限公司"}
{"url": "https://zh.fang.anjuke.com/loupan/canshu-254726.html", "projname": "御景首府", "xzarea": "珠海区域", "price": "11000", "area": "斗门", "position": "斗门", "developer": "珠海斗门金堡地产,新兴盛地产"}
{"url": "https://gz.fang.anjuke.com/loupan/canshu-418800.html", "projname": "佳兆业金域天下", "xzarea": "广州区域", "price": "13000", "area": "广州周边", "position": "佛山", "developer": "佛山市顺德区理想城房地产投资有限公司"}
{"url": "https://zh.fang.anjuke.com/loupan/canshu-431550.html", "projname": "时代南湾北岸", "xzarea": "珠海区域", "price": "9600", "area": "中山市", "position": "中山市", "developer": "中山市好世界聚宝园房地产有限公司"}
{"url": "https://gz.fang.anjuke.com/loupan/canshu-418756.html", "projname": "碧桂园半岛1号", "xzarea": "广州区域", "price": "11000", "area": "广州周边", "position": "清远", "developer": "清远市碧顺房地产开发有限公司"}
{"url": "https://gz.fang.anjuke.com/loupan/canshu-418768.html", "projname": "观景豪园", "xzarea": "广州区域", "price": "11500", "area": "广州周边", "position": "佛山", "developer": "佛山市三水区海景蓝湾房地产发展有限公司"}
{"url": "https://zh.fang.anjuke.com/loupan/canshu-409078.html", "projname": "万科·红树东岸", "xzarea": "珠海区域", "price": "27000", "area": "香洲", "position": "香洲", "developer": "珠海经济特区恒盛房产开发有限公司"}
{"url": "https://zh.fang.anjuke.com/loupan/canshu-400641.html", "projname": "华发峰尚", "xzarea": "珠海区域", "price": "14800", "area": "斗门", "position": "斗门", "developer": "珠海华发股份有限公司"}
{"url": "https://gz.fang.anjuke.com/loupan/canshu-238886.html", "projname": "碧桂园御湖城", "xzarea": "广州区域", "price": "13500", "area": "从化", "position": "江埔街", "developer": "广州君之源投资管理有限公司"}
{"url": "https://gz.fang.anjuke.com/loupan/canshu-430986.html", "projname": "碧桂园玺悦", "xzarea": "广州区域", "price": "22000", "area": "南沙", "position": "金洲", "developer": "广州融创实业投资有限公司"}
{"url": "https://zh.fang.anjuke.com/loupan/canshu-254741.html", "projname": "华融琴海湾", "xzarea": "珠海区域", "price": "49000", "area": "横琴", "position": "横琴", "developer": "华融置业有限责任公司"}
{"url": "https://gz.fang.anjuke.com/loupan/canshu-252394.html", "projname": "金保利世界城", "xzarea": "广州区域", "price": "6800", "area": "广州周边", "position": "清远", "developer": "清远市金保利置业投资有限公司"}
{"url": "https://gz.fang.anjuke.com/loupan/canshu-251880.html", "projname": "万科幸福誉", "xzarea": "广州区域", "price": "19000", "area": "黄埔", "position": "知识城", "developer": "广州知识城置业发展有限公司"}
{"url": "https://zh.fang.anjuke.com/loupan/canshu-418687.html", "projname": "万科·石花66號", "xzarea": "珠海区域", "price": 0, "area": "珠海财富贸易有限公司", "position": "", "developer": ""}
{"url": "https://gz.fang.anjuke.com/loupan/canshu-246792.html", "projname": "雅居乐富春山居", "xzarea": "广州区域", "price": "40000", "area": "黄埔", "position": "科学城", "developer": "广州雅恒房地产开发有限公司"}
{"url": "https://zh.fang.anjuke.com/loupan/canshu-254725.html", "projname": "御城金湾", "xzarea": "珠海区域", "price": "17000", "area": "中山市", "position": "中山市", "developer": "中山深城建房地产有限公司"}
{"url": "https://gz.fang.anjuke.com/loupan/canshu-250379.html", "projname": "南沙心意华庭", "xzarea": "广州区域", "price": 0, "area": "南沙", "position": "金洲", "developer": "广东嘉益企业有限公司"}
{"url": "https://zh.fang.anjuke.com/loupan/canshu-254691.html", "projname": "锦绣海湾城", "xzarea": "珠海区域", "price": "13500", "area": "中山市", "position": "中山市", "developer": "广州市敏捷投资有限公司"}
{"url": "https://zh.fang.anjuke.com/loupan/canshu-412215.html", "projname": "莲城印", "xzarea": "珠海区域", "price": "45000", "area": "横琴", "position": "横琴", "developer": "珠海蓝琴发展有限公司"}
{"url": "https://gz.fang.anjuke.com/loupan/canshu-272830.html", "projname": "广州万达城", "xzarea": "广州区域", "price": "24000", "area": "花都", "position": "区府", "developer": "广州万达文化旅游城投资有限公司"}
{"url": "https://zh.fang.anjuke.com/loupan/canshu-401107.html", "projname": "万科城", "xzarea": "珠海区域", "price": "27500", "area": "香洲", "position": "香洲", "developer": "珠海市万有引力房地产有限公司"}
{"url": "https://gz.fang.anjuke.com/loupan/canshu-417461.html", "projname": "碧桂园江与峸", "xzarea": "广州区域", "price": "12000", "area": "广州周边", "position": "清远", "developer": "清远市碧盛房地产开发有限公司"}
{"url": "https://gz.fang.anjuke.com/loupan/canshu-239316.html", "projname": "尚东•We家", "xzarea": "广州区域", "price": "20000", "area": "增城", "position": "新塘", "developer": "增城市新乐房地产有限公司"}
{"url": "https://gz.fang.anjuke.com/loupan/canshu-411506.html", "projname": "祈福缤纷汇", "xzarea": "广州区域", "price": 0, "area": "番禺", "position": "华南", "developer": "广州番禺祈福新村房地产有限公司"}
{"url": "https://zh.fang.anjuke.com/loupan/canshu-254688.html", "projname": "佳兆业御金山", "xzarea": "珠海区域", "price": "9500", "area": "斗门", "position": "斗门", "developer": "珠海市佳兆业房地产开发有限公司"}
{"url": "https://gz.fang.anjuke.com/loupan/canshu-400914.html", "projname": "怡翠尊堤", "xzarea": "广州区域", "price": "26000", "area": "广州周边", "position": "佛山", "developer": "佛山市凯能房地产开发有限公司"}
{"url": "https://zh.fang.anjuke.com/loupan/canshu-254669.html", "projname": "东方润园", "xzarea": "珠海区域", "price": "17500", "area": "金湾", "position": "金湾", "developer": "珠海市信和房地产开发有限公司"}
{"url": "https://gz.fang.anjuke.com/loupan/canshu-412440.html", "projname": "碧桂园翡翠湾", "xzarea": "广州区域", "price": "9000", "area": "广州周边", "position": "佛山", "developer": "广东业和房地产开发有限公司"}
{"url": "https://gz.fang.anjuke.com/loupan/canshu-250335.html", "projname": "时代天韵", "xzarea": "广州区域", "price": "19000", "area": "黄埔", "position": "知识城", "developer": "天韵(广州)房地产开发有限责任公司"}
{"url": "https://zh.fang.anjuke.com/loupan/canshu-412556.html", "projname": "时代保利中环广场", "xzarea": "珠海区域", "price": "37000", "area": "香洲", "position": "香洲", "developer": "珠海弘璟投资有限公司"}
{"url": "https://zh.fang.anjuke.com/loupan/canshu-414950.html", "projname": "华发·依山郡", "xzarea": "珠海区域", "price": "12600", "area": "斗门", "position": "斗门", "developer": ""}
{"url": "https://gz.fang.anjuke.com/loupan/canshu-239271.html", "projname": "珠江壹城", "xzarea": "广州区域", "price": "16500", "area": "从化", "position": "太平镇", "developer": "广州珠江房地产开发中心有限公司"}
{"url": "https://fs.fang.anjuke.com/loupan/canshu-243790.html", "projname": "雍翠新城", "xzarea": "佛山区域", "price": "9000", "area": "三水", "position": "乐平", "developer": "佛山市三水钜隆房产有限公司"}
{"url": "https://zh.fang.anjuke.com/loupan/canshu-417116.html", "projname": "时代倾城·双生花", "xzarea": "珠海区域", "price": "15500", "area": "斗门", "position": "斗门", "developer": "珠海顺晟投资有限公司"}
{"url": "https://fs.fang.anjuke.com/loupan/canshu-417231.html", "projname": "旭辉城", "xzarea": "佛山区域", "price": "11000", "area": "三水", "position": "云东海", "developer": "佛山市华祥发地产开发有限公司"}
{"url": "https://gz.fang.anjuke.com/loupan/canshu-272824.html", "projname": "金融街花溪小镇", "xzarea": "广州区域", "price": "15000", "area": "花都", "position": "新机场", "developer": "广州融都置业有限公司"}
{"url": "https://zh.fang.anjuke.com/loupan/canshu-254743.html", "projname": "金地格林泊乐", "xzarea": "珠海区域", "price": "14500", "area": "斗门", "position": "斗门", "developer": "金地集团珠海投资有限公司;珠海竹胜园房地产有限公司"}
{"url": "https://fs.fang.anjuke.com/loupan/canshu-252715.html", "projname": "国华新都", "xzarea": "佛山区域", "price": "15000", "area": "南海", "position": "大沥", "developer": "佛山市国华置业有限公司"}
{"url": "https://zs.fang.anjuke.com/loupan/canshu-432705.html", "projname": "阳光半岛", "xzarea": "中山区域", "price": "11000", "area": "[查看地图]", "position": "", "developer": "沙溪镇 沙溪镇"}
{"url": "https://gz.fang.anjuke.com/loupan/canshu-383898.html", "projname": "金地香山湖", "xzarea": "广州区域", "price": "15000", "area": "增城", "position": "广园东", "developer": "金地(集团)股份有限公司"}
{"url": "https://gz.fang.anjuke.com/loupan/canshu-431038.html", "projname": "时代家", "xzarea": "广州区域", "price": 0, "area": "广州周边", "position": "佛山", "developer": "佛山市时代天宇房地产开发有限公司"}
{"url": "https://gz.fang.anjuke.com/loupan/canshu-249946.html", "projname": "绿湖国际城", "xzarea": "广州区域", "price": "14500", "area": "增城", "position": "荔城", "developer": "广州育丰房地产开发有限公司"}
{"url": "https://gz.fang.anjuke.com/loupan/canshu-256987.html", "projname": "越秀保利爱特城", "xzarea": "广州区域", "price": "23000", "area": "黄埔", "position": "科学城", "developer": "广州中耀实业投资有限公司"}
{"url": "https://gz.fang.anjuke.com/loupan/canshu-252379.html", "projname": "佳兆业城市广场", "xzarea": "广州区域", "price": "26000", "area": "黄埔", "position": "黄埔区府", "developer": "广州市兆昌房地产开发有限公司"}
{"url": "https://fs.fang.anjuke.com/loupan/canshu-416014.html", "projname": "融创望江府", "xzarea": "佛山区域", "price": "13000", "area": "禅城", "position": "祖庙", "developer": ""}
{"url": "https://gz.fang.anjuke.com/loupan/canshu-240269.html", "projname": "新世界凯粤湾", "xzarea": "广州区域", "price": "43800", "area": "荔湾", "position": "其他", "developer": "广州芳村-新世界房地产发展有限公司"}
{"url": "https://fs.fang.anjuke.com/loupan/canshu-417013.html", "projname": "恒大郦湖城", "xzarea": "佛山区域", "price": "11000", "area": "三水", "position": "西南", "developer": ""}
{"url": "https://gz.fang.anjuke.com/loupan/canshu-243829.html", "projname": "广佛新世界上城", "xzarea": "广州区域", "price": 0, "area": "新世界中国地产有限公司", "position": "", "developer": ""}
{"url": "https://fs.fang.anjuke.com/loupan/canshu-243816.html", "projname": "云山峰境花园", "xzarea": "佛山区域", "price": "12500", "area": "南海", "position": "丹灶", "developer": "佛山市宏越房地产开发有限公司"}
{"url": "https://zs.fang.anjuke.com/loupan/canshu-258712.html", "projname": "华发四季", "xzarea": "中山区域", "price": 0, "area": "沙溪镇", "position": "沙溪镇", "developer": "中山市华发生态园房地产开发有限公司"}
{"url": "https://gz.fang.anjuke.com/loupan/canshu-411791.html", "projname": "保利·中航城", "xzarea": "广州区域", "price": "23000", "area": "增城", "position": "朱村", "developer": "广州市航里房地产开发有限公司"}
{"url": "https://fs.fang.anjuke.com/loupan/canshu-416786.html", "projname": "美的翰湖苑", "xzarea": "佛山区域", "price": 0, "area": "南海", "position": "丹灶", "developer": ""}
{"url": "https://gz.fang.anjuke.com/loupan/canshu-411750.html", "projname": "路劲天隽峰", "xzarea": "广州区域", "price": "26000", "area": "花都", "position": "区府", "developer": "广州隽宏房地产开发有限公司"}
{"url": "https://fs.fang.anjuke.com/loupan/canshu-414193.html", "projname": "伦教碧桂园", "xzarea": "佛山区域", "price": "15800", "area": "顺德", "position": "伦教", "developer": ""}
{"url": "https://gz.fang.anjuke.com/loupan/canshu-400938.html", "projname": "越秀滨海御城", "xzarea": "广州区域", "price": "26000", "area": "南沙", "position": "金洲", "developer": "广州城建开发南沙房地产有限公司"}
{"url": "https://zs.fang.anjuke.com/loupan/canshu-414966.html", "projname": "中安广场", "xzarea": "中山区域", "price": "33000", "area": "", "position": "", "developer": "珠海市钧策商贸发展有限公司"}
{"url": "https://fs.fang.anjuke.com/loupan/canshu-414489.html", "projname": "恒大悦府", "xzarea": "佛山区域", "price": 0, "area": "南海", "position": "千灯湖", "developer": ""}
{"url": "https://gz.fang.anjuke.com/loupan/canshu-428080.html", "projname": "万科白鹭郡", "xzarea": "广州区域", "price": "65000", "area": "南沙", "position": "黄阁", "developer": "广州万科房地产开发有限公司"}
{"url": "https://zs.fang.anjuke.com/loupan/canshu-258617.html", "projname": "盈天可乐国际", "xzarea": "中山区域", "price": 0, "area": "三角镇", "position": "三角镇", "developer": "中山市盈天房地产开发有限公司"}
{"url": "https://zs.fang.anjuke.com/loupan/canshu-258667.html", "projname": "城市空间", "xzarea": "中山区域", "price": 0, "area": "西区", "position": "西区", "developer": "中山昆宏投资发展有限公司"}
{"url": "https://fs.fang.anjuke.com/loupan/canshu-383744.html", "projname": "广佛新世界上城", "xzarea": "佛山区域", "price": "16000", "area": "南海", "position": "狮山", "developer": "新世界中国地产有限公司"}
{"url": "https://gz.fang.anjuke.com/loupan/canshu-238888.html", "projname": "广州亚运城", "xzarea": "广州区域", "price": 0, "area": "番禺", "position": "亚运新城", "developer": "广州利合房地产开发有限公司"}
{"url": "https://fs.fang.anjuke.com/loupan/canshu-417036.html", "projname": "乐平碧桂园", "xzarea": "佛山区域", "price": "10000", "area": "三水", "position": "乐平", "developer": "佛山市顺德区碧桂园地产有限公司"}
{"url": "https://fs.fang.anjuke.com/loupan/canshu-412565.html", "projname": "碧桂园联丰天汇湾", "xzarea": "佛山区域", "price": 0, "area": "高明", "position": "荷城", "developer": "佛山市高明区联丰置业发展有限公司"}
{"url": "https://fs.fang.anjuke.com/loupan/canshu-413963.html", "projname": "保利海德公园", "xzarea": "佛山区域", "price": 0, "area": "顺德", "position": "佛山新城", "developer": "保利华南实业有限公司"}
{"url": "https://fs.fang.anjuke.com/loupan/canshu-414886.html", "projname": "碧桂园翡翠山", "xzarea": "佛山区域", "price": 0, "area": "三水", "position": "云东海", "developer": "佛山市三水区碧桂园房地产开发有限公司"}
{"url": "https://fs.fang.anjuke.com/loupan/canshu-243901.html", "projname": "桂丹颐景园", "xzarea": "佛山区域", "price": 0, "area": "南海", "position": "丹灶", "developer": "佛山颐景园置业发展有限公司"}
{"url": "https://zs.fang.anjuke.com/loupan/canshu-258568.html", "projname": "天奕国际广场", "xzarea": "中山区域", "price": "60", "area": "[查看地图]", "position": "", "developer": "东区 东区"}
{"url": "https://fs.fang.anjuke.com/loupan/canshu-416841.html", "projname": "美的壹号公馆", "xzarea": "佛山区域", "price": "25000", "area": "顺德", "position": "北滘", "developer": "美的地产"}
{"url": "https://fs.fang.anjuke.com/loupan/canshu-428131.html", "projname": "恒大龙江翡翠", "xzarea": "佛山区域", "price": "16000", "area": "顺德", "position": "龙江", "developer": "佛山市顺德区协城房地产有限公司"}
{"url": "https://fs.fang.anjuke.com/loupan/canshu-383779.html", "projname": "万科金域中央", "xzarea": "佛山区域", "price": "16000", "area": "南海", "position": "千灯湖", "developer": "佛山市南海区万瑞投资有限公司"}
{"url": "https://fs.fang.anjuke.com/loupan/canshu-394529.html", "projname": "时代水岸", "xzarea": "佛山区域", "price": "24000", "area": "南海", "position": "大沥", "developer": "佛山市时代鸿誉房地产开发有限公司"}
{"url": "https://fs.fang.anjuke.com/loupan/canshu-414869.html", "projname": "碧桂园岭南盛世", "xzarea": "佛山区域", "price": "19000", "area": "禅城", "position": "祖庙", "developer": "佛山源康房地产发展有限公司"}
{"url": "https://zs.fang.anjuke.com/loupan/canshu-258718.html", "projname": "汇景东方", "xzarea": "中山区域", "price": "500", "area": "[查看地图]", "position": "", "developer": "火炬区 火炬区"}
{"url": "https://fs.fang.anjuke.com/loupan/canshu-417221.html", "projname": "碧桂园珑悦", "xzarea": "佛山区域", "price": "15000", "area": "顺德", "position": "龙江", "developer": "佛山市顺德区龙江碧桂园置业有限公司"}
{"url": "https://fs.fang.anjuke.com/loupan/canshu-246300.html", "projname": "佳兆业金域天下", "xzarea": "佛山区域", "price": "13000", "area": "顺德", "position": "容桂", "developer": ""}
{"url": "https://zs.fang.anjuke.com/loupan/canshu-258580.html", "projname": "小琅环壹号", "xzarea": "中山区域", "price": 0, "area": "三乡镇", "position": "三乡镇", "developer": "中山市世光创建集团有限公司"}
{"url": "https://zs.fang.anjuke.com/loupan/canshu-258688.html", "projname": "枫璟美地园", "xzarea": "中山区域", "price": 0, "area": "东升镇", "position": "东升镇", "developer": "暂无资料"}
{"url": "https://fs.fang.anjuke.com/loupan/canshu-416785.html", "projname": "朝安碧桂园", "xzarea": "佛山区域", "price": "19000", "area": "禅城", "position": "祖庙", "developer": "佛山市星晟房地产投资有限公司"}
{"url": "https://fs.fang.anjuke.com/loupan/canshu-405515.html", "projname": "保利·中央公园", "xzarea": "佛山区域", "price": "16000", "area": "顺德", "position": "伦教", "developer": "广东保利置业有限公司"}
{"url": "https://zh.fang.anjuke.com/loupan/canshu-254700.html", "projname": "仁恒滨海中心", "xzarea": "珠海区域", "price": "65000", "area": "香洲", "position": "香洲", "developer": "新加坡仁恒置地集团"}
{"url": "https://fs.fang.anjuke.com/loupan/canshu-417230.html", "projname": "旭辉公元", "xzarea": "佛山区域", "price": "17000", "area": "禅城", "position": "祖庙", "developer": "佛山市合盈置业有限公司"}
{"url": "https://zh.fang.anjuke.com/loupan/canshu-254734.html", "projname": "中信红树湾", "xzarea": "珠海区域", "price": "45000", "area": "香洲", "position": "香洲", "developer": "中信华南（集团）珠海有限公司"}
{"url": "https://zh.fang.anjuke.com/loupan/canshu-406022.html", "projname": "东城天樾", "xzarea": "珠海区域", "price": 0, "area": "中山市", "position": "中山市", "developer": "中山市世光创建集团有限公司"}
{"url": "https://zh.fang.anjuke.com/loupan/canshu-428917.html", "projname": "横琴万象世界", "xzarea": "珠海区域", "price": "35000", "area": "横琴", "position": "横琴", "developer": "横琴万象世界发展有限公司"}
{"url": "https://zh.fang.anjuke.com/loupan/canshu-254660.html", "projname": "保利西海岸", "xzarea": "珠海区域", "price": "28000", "area": "香洲", "position": "香洲", "developer": "珠海保利天悦投资控股有限公司"}
{"url": "https://zh.fang.anjuke.com/loupan/canshu-256092.html", "projname": "招商·依云水岸", "xzarea": "珠海区域", "price": "14000", "area": "斗门", "position": "斗门", "developer": "珠海依云房地产有限公司"}
{"url": "https://gz.fang.anjuke.com/loupan/canshu-428198.html", "projname": "信业郡城", "xzarea": "广州区域", "price": "9000", "area": "广州周边", "position": "清远", "developer": "清远市美心房地产开发有限公司"}
{"url": "https://zh.fang.anjuke.com/loupan/canshu-399990.html", "projname": "天宸", "xzarea": "珠海区域", "price": "37000", "area": "香洲", "position": "香洲", "developer": "珠海明星大厦有限公司"}
{"url": "https://zs.fang.anjuke.com/loupan/canshu-429282.html", "projname": "中山恒大御府", "xzarea": "中山区域", "price": "13000", "area": "[查看地图]", "position": "", "developer": "黄圃镇 黄圃镇"}
{"url": "https://fs.fang.anjuke.com/loupan/canshu-411752.html", "projname": "美的花湾城", "xzarea": "佛山区域", "price": "23000", "area": "顺德", "position": "陈村", "developer": ""}
{"url": "https://fs.fang.anjuke.com/loupan/canshu-418891.html", "projname": "合景天銮", "xzarea": "佛山区域", "price": "27000", "area": "顺德", "position": "北滘", "developer": "合景泰富地产控股有限公司"}
{"url": "https://fs.fang.anjuke.com/loupan/canshu-416026.html", "projname": "龙光玖龙湾", "xzarea": "佛山区域", "price": "17000", "area": "禅城", "position": "祖庙", "developer": "佛山市龙光骏景房地产有限公司"}
{"url": "https://fs.fang.anjuke.com/loupan/canshu-405136.html", "projname": "龙湖春江名城", "xzarea": "佛山区域", "price": "12800", "area": "顺德", "position": "大良", "developer": ""}
{"url": "https://zh.fang.anjuke.com/loupan/canshu-414619.html", "projname": "万菱·情侣湾1号", "xzarea": "珠海区域", "price": "57000", "area": "香洲", "position": "香洲", "developer": "珠海富铿房地产有限公司"}
{"url": "https://zh.fang.anjuke.com/loupan/canshu-256063.html", "projname": "金碧丽江东海岸花园", "xzarea": "珠海区域", "price": "18500", "area": "斗门", "position": "斗门", "developer": "珠海市金碧房地产开发有限公司"}
{"url": "https://zh.fang.anjuke.com/loupan/canshu-256059.html", "projname": "华发悦府", "xzarea": "珠海区域", "price": "46000", "area": "横琴", "position": "横琴", "developer": ""}
{"url": "https://zh.fang.anjuke.com/loupan/canshu-256051.html", "projname": "凤凰海域", "xzarea": "珠海区域", "price": "40000", "area": "香洲", "position": "香洲", "developer": "珠海市国鼎集团有限公司"}
{"url": "https://zh.fang.anjuke.com/loupan/canshu-417129.html", "projname": "祥圣富地", "xzarea": "珠海区域", "price": "16500", "area": "中山市", "position": "中山市", "developer": "中山市祥圣房地产有限公司"}
{"url": "https://gz.fang.anjuke.com/loupan/canshu-247808.html", "projname": "碧桂园山湖城", "xzarea": "广州区域", "price": "11000", "area": "广州周边", "position": "清远", "developer": "清远碧桂园新亚房地产开发有限公司"}
{"url": "https://zh.fang.anjuke.com/loupan/canshu-254727.html", "projname": "誉峯名门", "xzarea": "珠海区域", "price": "18500", "area": "中山市", "position": "中山市", "developer": "中山市大俊置业有限公司"}
{"url": "https://gz.fang.anjuke.com/loupan/canshu-253149.html", "projname": "江山时代", "xzarea": "广州区域", "price": 0, "area": "增城", "position": "朱村", "developer": "广州恒展房地产开发有限公司"}
{"url": "https://zh.fang.anjuke.com/loupan/canshu-411859.html", "projname": "爱琴半岛", "xzarea": "珠海区域", "price": "9000", "area": "中山市", "position": "中山市", "developer": "中山市半岛房地产发展有限公司"}
{"url": "https://gz.fang.anjuke.com/loupan/canshu-417519.html", "projname": "时代花城", "xzarea": "广州区域", "price": "11000", "area": "广州周边", "position": "清远", "developer": "清远市喜龙房地产开发有限公司"}
{"url": "https://zh.fang.anjuke.com/loupan/canshu-256091.html", "projname": "雅居乐万象郡", "xzarea": "珠海区域", "price": 0, "area": "中山市", "position": "中山市", "developer": "中山市雅建房地产发展有限公司"}
{"url": "https://gz.fang.anjuke.com/loupan/canshu-416189.html", "projname": "新世界云逸", "xzarea": "广州区域", "price": 0, "area": "白云", "position": "白云大道", "developer": "广州新穗旅游中心有限公司"}
{"url": "https://zh.fang.anjuke.com/loupan/canshu-425264.html", "projname": "碧桂园·天悦府", "xzarea": "珠海区域", "price": "15000", "area": "中山市", "position": "中山市", "developer": "中山市碧乡房地产开发有限公司"}
{"url": "https://gz.fang.anjuke.com/loupan/canshu-238894.html", "projname": "花都颐和山庄", "xzarea": "广州区域", "price": "12000", "area": "花都", "position": "新机场", "developer": "广州白云国际机场集团综合开发有限公司"}
{"url": "https://zh.fang.anjuke.com/loupan/canshu-414694.html", "projname": "阳光一号", "xzarea": "珠海区域", "price": "18000", "area": "金湾", "position": "金湾", "developer": "珠海市三美贸易有限公司"}
{"url": "https://zh.fang.anjuke.com/loupan/canshu-405851.html", "projname": "中海·左岸岚庭", "xzarea": "珠海区域", "price": "22500", "area": "金湾", "position": "金湾", "developer": "珠海市嘉烨房地产开发有限公司"}
{"url": "https://gz.fang.anjuke.com/loupan/canshu-420789.html", "projname": "融创湖滨首府", "xzarea": "广州区域", "price": "9800", "area": "广州周边", "position": "清远", "developer": "清远市道申房地产有限公司"}
{"url": "https://gz.fang.anjuke.com/loupan/canshu-400594.html", "projname": "天河星作", "xzarea": "广州区域", "price": "41000", "area": "天河", "position": "东圃", "developer": "广州财基投资管理有限公司"}
{"url": "https://zh.fang.anjuke.com/loupan/canshu-409387.html", "projname": "乐富里", "xzarea": "珠海区域", "price": 0, "area": "香洲", "position": "香洲", "developer": "珠海市明隆发展有限公司"}
{"url": "https://gz.fang.anjuke.com/loupan/canshu-414580.html", "projname": "保利华润紫云", "xzarea": "广州区域", "price": "40000", "area": "白云", "position": "白云大道", "developer": "广州璟晔房地产开发有限公司,广州宏嘉房地产开发有限公司,广州宏轩房地产开发有限公司"}
{"url": "https://zh.fang.anjuke.com/loupan/canshu-415104.html", "projname": "龙光·玖龙府", "xzarea": "珠海区域", "price": "20000", "area": "金湾", "position": "金湾", "developer": "珠海骏驰房地产开发有限公司"}
{"url": "https://gz.fang.anjuke.com/loupan/canshu-415265.html", "projname": "信达金茂广场", "xzarea": "广州区域", "price": "49999", "area": "天河", "position": "其他", "developer": ""}
{"url": "https://zh.fang.anjuke.com/loupan/canshu-414258.html", "projname": "德瑞花园", "xzarea": "珠海区域", "price": "14000", "area": "中山市", "position": "中山市", "developer": "珠海市高瑞房地产投资有限公司"}
{"url": "https://gz.fang.anjuke.com/loupan/canshu-409439.html", "projname": "实地常春藤", "xzarea": "广州区域", "price": "25000", "area": "黄埔", "position": "长岭居", "developer": "实地地产"}
{"url": "https://zh.fang.anjuke.com/loupan/canshu-417145.html", "projname": "逸骏星园", "xzarea": "珠海区域", "price": "18500", "area": "中山市", "position": "中山市", "developer": "中山市逸骏置业发展有限公司"}
{"url": "https://gz.fang.anjuke.com/loupan/canshu-410358.html", "projname": "万科里享家 | 蔚来", "xzarea": "广州区域", "price": "22000", "area": "黄埔", "position": "长岭居", "developer": "广州市金仑房地产开发有限公司"}
{"url": "https://zh.fang.anjuke.com/loupan/canshu-420119.html", "projname": "同裕·子悦山", "xzarea": "珠海区域", "price": "16000", "area": "金湾", "position": "金湾", "developer": "珠海市裕沙房地产开发有限公司"}
{"url": "https://gz.fang.anjuke.com/loupan/canshu-247857.html", "projname": "广铝荔富湖畔", "xzarea": "广州区域", "price": "23000", "area": "增城", "position": "朱村", "developer": "广州市荔富湖畔房地产有限公司"}
{"url": "https://zh.fang.anjuke.com/loupan/canshu-254685.html", "projname": "黄杨·明月轩", "xzarea": "珠海区域", "price": 0, "area": "斗门", "position": "斗门", "developer": "斗门建豪房地产开发有限公司"}
{"url": "https://gz.fang.anjuke.com/loupan/canshu-415088.html", "projname": "招商雍华府", "xzarea": "广州区域", "price": "45000", "area": "天河", "position": "东圃", "developer": "广州联洲房地产有限公司"}
{"url": "https://gz.fang.anjuke.com/loupan/canshu-272828.html", "projname": "大夫山•尚东", "xzarea": "广州区域", "price": "24000", "area": "番禺", "position": "市桥", "developer": "广州市瑞安房地产置业有限公司"}
{"url": "https://zh.fang.anjuke.com/loupan/canshu-400011.html", "projname": "珠海奥园广场", "xzarea": "珠海区域", "price": "16000", "area": "香洲", "position": "香洲", "developer": "珠海市梅溪置业有限公司"}
{"url": "https://zh.fang.anjuke.com/loupan/canshu-411009.html", "projname": "横琴·珠江湾", "xzarea": "珠海区域", "price": "43000", "area": "横琴", "position": "横琴", "developer": "珠海珠江景帝投资有限公司"}
{"url": "https://zh.fang.anjuke.com/loupan/canshu-416403.html", "projname": "中冶盛世国际广场", "xzarea": "珠海区域", "price": "44000", "area": "横琴", "position": "横琴", "developer": "中冶置业集团有限公司"}
{"url": "https://gz.fang.anjuke.com/loupan/canshu-409426.html", "projname": "兰亭盛荟", "xzarea": "广州区域", "price": "46000", "area": "天河", "position": "东圃", "developer": "广州佳郡置业有限公司"}
{"url": "https://gz.fang.anjuke.com/loupan/canshu-411857.html", "projname": "保利星海小镇", "xzarea": "广州区域", "price": "20000", "area": "南沙", "position": "其他", "developer": "广州保辉房地产开发有限公司"}
{"url": "https://gz.fang.anjuke.com/loupan/canshu-251875.html", "projname": "南沙金茂湾", "xzarea": "广州区域", "price": "20000", "area": "南沙", "position": "蕉门河", "developer": "中国金茂"}
{"url": "https://zh.fang.anjuke.com/loupan/canshu-409423.html", "projname": "鼎威花园", "xzarea": "珠海区域", "price": "14000", "area": "中山市", "position": "中山市", "developer": "中山市鼎威房地产开发有限公司"}
{"url": "https://zs.fang.anjuke.com/loupan/canshu-258572.html", "projname": "万科柏悦湾", "xzarea": "中山区域", "price": 0, "area": "火炬区", "position": "火炬区", "developer": "中山市万科水晶城房地产有限公司"}
{"url": "https://gz.fang.anjuke.com/loupan/canshu-389673.html", "projname": "景业荔都", "xzarea": "广州区域", "price": "12000", "area": "从化", "position": "温泉镇", "developer": "广州意浓实业有限公司"}
{"url": "https://gz.fang.anjuke.com/loupan/canshu-389651.html", "projname": "中海花湾壹号", "xzarea": "广州区域", "price": "50000", "area": "荔湾", "position": "芳村", "developer": ""}
{"url": "https://gz.fang.anjuke.com/loupan/canshu-417689.html", "projname": "越秀滨海新城", "xzarea": "广州区域", "price": "17000", "area": "南沙", "position": "金洲", "developer": "广州中璟慧富房地产开发有限公司"}
{"url": "https://gz.fang.anjuke.com/loupan/canshu-414790.html", "projname": "碧桂园星钻", "xzarea": "广州区域", "price": 0, "area": "番禺", "position": "市桥", "developer": "广东碧桂园房地产开发有限公司"}
{"url": "https://gz.fang.anjuke.com/loupan/canshu-417616.html", "projname": "美的壹号公馆", "xzarea": "广州区域", "price": "25000", "area": "广州周边", "position": "佛山", "developer": "广东美的置业有限公司"}
{"url": "https://gz.fang.anjuke.com/loupan/canshu-399951.html", "projname": "时代水岸", "xzarea": "广州区域", "price": "24000", "area": "广州周边", "position": "佛山", "developer": "佛山市时代华泰房地产开发有限公司"}
{"url": "https://gz.fang.anjuke.com/loupan/canshu-417309.html", "projname": "招商雍景湾", "xzarea": "广州区域", "price": 0, "area": "黄埔", "position": "知识城", "developer": "天骄（广州）房地产开发有限公司"}
{"url": "https://gz.fang.anjuke.com/loupan/canshu-245255.html", "projname": "金泽惠百氏", "xzarea": "广州区域", "price": 0, "area": "增城", "position": "新塘", "developer": "增城市惠百氏物业管理有限公司"}
{"url": "https://gz.fang.anjuke.com/loupan/canshu-414793.html", "projname": "时代名著", "xzarea": "广州区域", "price": "22000", "area": "广州周边", "position": "佛山", "developer": "佛山市时代富锦房地产开发有限公司"}
{"url": "https://fs.fang.anjuke.com/loupan/canshu-431560.html", "projname": "旭辉江山", "xzarea": "佛山区域", "price": 0, "area": "三水", "position": "西南", "developer": "佛山市汇金恒天房地产开发有限公司"}
{"url": "https://gz.fang.anjuke.com/loupan/canshu-248202.html", "projname": "时代康桥", "xzarea": "广州区域", "price": "11000", "area": "花都", "position": "狮岭", "developer": "广州市利峰房地产开发有限公司"}
{"url": "https://zs.fang.anjuke.com/loupan/canshu-258703.html", "projname": "广物锦绣东方", "xzarea": "中山区域", "price": "11500", "area": "[查看地图]", "position": "", "developer": "南头镇 南头镇"}
{"url": "https://gz.fang.anjuke.com/loupan/canshu-400877.html", "projname": "华发荔湾荟", "xzarea": "广州区域", "price": "46000", "area": "荔湾", "position": "芳村", "developer": "广州华昊房地产开发有限公司"}
{"url": "https://gz.fang.anjuke.com/loupan/canshu-383897.html", "projname": "广州绿地城", "xzarea": "广州区域", "price": 0, "area": "黄埔", "position": "知识城", "developer": "广州市满庭芳房地产开发有限公司"}
{"url": "https://fs.fang.anjuke.com/loupan/canshu-412048.html", "projname": "当代万国府MOMΛ", "xzarea": "佛山区域", "price": "26000", "area": "南海", "position": "千灯湖", "developer": ""}
{"url": "https://fs.fang.anjuke.com/loupan/canshu-423894.html", "projname": "星港城", "xzarea": "佛山区域", "price": "120", "area": "[查看地图]", "position": "", "developer": "南海 里水"}
{"url": "https://fs.fang.anjuke.com/loupan/canshu-431280.html", "projname": "美的西江府", "xzarea": "佛山区域", "price": 0, "area": "顺德", "position": "龙江", "developer": "佛山市顺德区天美房产有限公司"}
{"url": "https://zs.fang.anjuke.com/loupan/canshu-429776.html", "projname": "越秀星汇品峰天寰", "xzarea": "中山区域", "price": "14000", "area": "[查看地图]", "position": "", "developer": "东区 东区"}
{"url": "https://fs.fang.anjuke.com/loupan/canshu-412212.html", "projname": "碧桂园凤凰湾", "xzarea": "佛山区域", "price": "15000", "area": "顺德", "position": "容桂", "developer": ""}
{"url": "https://zs.fang.anjuke.com/loupan/canshu-429426.html", "projname": "碧桂园保利天启", "xzarea": "中山区域", "price": "18000", "area": "[查看地图]", "position": "", "developer": "南朗镇 南朗镇"}
{"url": "https://fs.fang.anjuke.com/loupan/canshu-411228.html", "projname": "保利诺丁山", "xzarea": "佛山区域", "price": "20000", "area": "南海", "position": "桂城", "developer": "佛山市保利昊峰房地产有限公司"}
{"url": "https://zs.fang.anjuke.com/loupan/canshu-258540.html", "projname": "凝星名都", "xzarea": "中山区域", "price": 0, "area": "神湾镇", "position": "神湾镇", "developer": "中山市好世界聚宝园房地产有限公司"}
{"url": "https://fs.fang.anjuke.com/loupan/canshu-416526.html", "projname": "时代南湾", "xzarea": "佛山区域", "price": "11000", "area": "三水", "position": "西南", "developer": ""}
{"url": "https://fs.fang.anjuke.com/loupan/canshu-243908.html", "projname": "御江南", "xzarea": "佛山区域", "price": "11000", "area": "三水", "position": "西南", "developer": "佛山市三水高富地产开发有限公司"}
{"url": "https://zs.fang.anjuke.com/loupan/canshu-258669.html", "projname": "纯水岸", "xzarea": "中山区域", "price": "9500", "area": "[查看地图]", "position": "", "developer": "板芙镇 板芙镇"}
{"url": "https://fs.fang.anjuke.com/loupan/canshu-397192.html", "projname": "三水万达广场", "xzarea": "佛山区域", "price": "9000", "area": "三水", "position": "西南", "developer": "佛山三水万达广场投资有限公司"}
{"url": "https://fs.fang.anjuke.com/loupan/canshu-243760.html", "projname": "海骏达康格斯", "xzarea": "佛山区域", "price": "12000", "area": "顺德", "position": "大良", "developer": "广东海骏达置业投资集团有限公司"}
{"url": "https://fs.fang.anjuke.com/loupan/canshu-418773.html", "projname": "观景豪园", "xzarea": "佛山区域", "price": "11000", "area": "三水", "position": "西南", "developer": "佛山市三水区海景蓝湾房地产发展有限公司"}
{"url": "https://fs.fang.anjuke.com/loupan/canshu-431003.html", "projname": "时代领峰", "xzarea": "佛山区域", "price": 0, "area": "[查看地图]", "position": "", "developer": "南海 狮山"}
{"url": "https://fs.fang.anjuke.com/loupan/canshu-243870.html", "projname": "深业城", "xzarea": "佛山区域", "price": "15000", "area": "顺德", "position": "北滘", "developer": "佛山市顺德区深业房地产有限公司"}
{"url": "https://fs.fang.anjuke.com/loupan/canshu-251517.html", "projname": "保利中央公园", "xzarea": "佛山区域", "price": "12000", "area": "三水", "position": "云东海", "developer": ""}
{"url": "https://fs.fang.anjuke.com/loupan/canshu-432841.html", "projname": "广佛新世界凯璟湾", "xzarea": "佛山区域", "price": "28000", "area": "南海", "position": "狮山", "developer": "新世界中国地产有限公司"}
{"url": "https://fs.fang.anjuke.com/loupan/canshu-415050.html", "projname": "佛山恒大御湖湾", "xzarea": "佛山区域", "price": "13000", "area": "南海", "position": "西樵", "developer": "佛山市南海俊凯房地产开发有限公司"}
{"url": "https://fs.fang.anjuke.com/loupan/canshu-431143.html", "projname": "金辉优步大道", "xzarea": "佛山区域", "price": "20000", "area": "顺德", "position": "北滘", "developer": "佛山市金辉房地产有限公司"}
{"url": "https://fs.fang.anjuke.com/loupan/canshu-409142.html", "projname": "碧桂园龙江华府", "xzarea": "佛山区域", "price": "15500", "area": "顺德", "position": "龙江", "developer": "佛山市顺德区龙江碧桂园房地产开发有限公司"}
{"url": "https://fs.fang.anjuke.com/loupan/canshu-410163.html", "projname": "万科金域缇香", "xzarea": "佛山区域", "price": "21000", "area": "南海", "position": "里水", "developer": "佛山市南海区万扬房地产有限公司"}
{"url": "https://fs.fang.anjuke.com/loupan/canshu-414332.html", "projname": "时代名著", "xzarea": "佛山区域", "price": "23000", "area": "南海", "position": "桂城", "developer": ""}
{"url": "https://fs.fang.anjuke.com/loupan/canshu-250418.html", "projname": "怡翠晋盛", "xzarea": "佛山区域", "price": "18000", "area": "顺德", "position": "佛山新城", "developer": "佛山市佑嘉置业有限公司"}
